dynapyt/__init__.py
dynapyt/post_run.py
dynapyt/run_all.py
dynapyt/run_analysis.py
dynapyt/run_instrumentation.py
dynapyt/runtime.py
dynapyt/analyses/BaseAnalysis.py
dynapyt/analyses/BranchCoverage.py
dynapyt/analyses/CallGraph.py
dynapyt/analyses/Demo.py
dynapyt/analyses/EventAnalysis.py
dynapyt/analyses/KeyInListAnalysis.py
dynapyt/analyses/LiteralAnalysis.py
dynapyt/analyses/MLMemoryAnalysis.py
dynapyt/analyses/ManipulateExec.py
dynapyt/analyses/MemoryAccessAnalysis.py
dynapyt/analyses/OnlyAddAnalysis.py
dynapyt/analyses/OperationAnalysis.py
dynapyt/analyses/SimpleTaintAnalysis.py
dynapyt/analyses/SimpleTestAnalysis.py
dynapyt/analyses/TraceAll.py
dynapyt/analyses/UnnecessaryDoubleDictQuery.py
dynapyt/analyses/__init__.py
dynapyt/instrument/CodeInstrumenter.py
dynapyt/instrument/IIDs.py
dynapyt/instrument/__init__.py
dynapyt/instrument/filters.py
dynapyt/instrument/instrument.py
dynapyt/utils/AnalysisUtils.py
dynapyt/utils/__init__.py
dynapyt/utils/hooks.py
dynapyt/utils/nodeLocator.py
dynapyt/utils/runtimeUtils.py
dynapyt/utils/hierarchy.json
dynapyt-2.2.0.dist-info/METADATA
dynapyt-2.2.0.dist-info/WHEEL
dynapyt-2.2.0.dist-info/licenses/LICENSE
dynapyt-2.2.0.dist-info/RECORD
