Metadata-Version: 2.3
Name: dynapyt
Version: 2.2.0
Summary: Dynamic analysis framework for Python
Project-URL: Bug Tracker, https://github.com/sola-st/DynaPyt/issues
Project-URL: Homepage, https://github.com/sola-st/DynaPyt
Author-email: Aryaz Eghbali <aryaz.egh@gmail.com>, Michael Pradel <michael@binaervarianz.de>
Classifier: License :: OSI Approved :: MIT License
Classifier: Operating System :: OS Independent
Classifier: Programming Language :: Python :: 3
Requires-Python: >=3.6
Requires-Dist: filelock
Requires-Dist: libcst
Provides-Extra: end2end
Requires-Dist: fire; extra == 'end2end'
Requires-Dist: pytest-xdist; extra == 'end2end'
